diseño-digital/LFSR/lfsr_galois.v
module lfsr_galois(
  input wire        clk,          // Reloj del sistema
  input wire        i_valid,      // Señal de validación para generar nueva secuencia
  input wire        i_rst,        // Reset asincrónico para inicializar con la semilla fija
  input wire        i_soft_reset, // Reset sincrónico para inicializar con la semilla del puerto
  input wire [7:0]  i_seed       // Semilla inicial proporcionada desde el puerto
);

// Salida del registro LFSR
wire [7:0]  o_lfsr;

// Registro para el estado actual del LFSR
reg [7:0] lfsr_reg;

// Registro para la semilla fija
reg [7:0] seed_reg = 8'b00000001;

// Feedback del LFSR
wire feedback = lfsr_reg[7];

always @(posedge clk or posedge i_rst) begin

  if(i_rst) begin

    lfsr_reg <= seed_reg;

  end else if(i_soft_reset) begin

    lfsr_reg <= i_seed;

  end else if(i_valid) begin

    lfsr_reg[0] <= feedback;
    lfsr_reg[1] <= lfsr_reg[0];
    lfsr_reg[2] <= lfsr_reg[1]^feedback;
    lfsr_reg[3] <= lfsr_reg[2]^feedback;
    lfsr_reg[4] <= lfsr_reg[3]^feedback;
    lfsr_reg[5] <= lfsr_reg[4];
    lfsr_reg[6] <= lfsr_reg[5];
    lfsr_reg[7] <= lfsr_reg[6];

  end

end

assign o_lfsr = lfsr_reg;

endmodule

diseño-digital/LFSR/tb/lfsr_galois_tb1.v
`timescale 1ns / 1ps
`include "lfsr_galois.v"

//-----------------------------------------------------
//iverilog -o tb/tb1 tb/lfsr_galois_tb1.v
//vvp tb/tb1
//-----------------------------------------------------

module lfsr_galois_tb1;

  reg clk;
  reg i_valid;
  reg i_rst;
  reg i_soft_reset;
  reg [7:0] i_seed;
  wire [7:0] o_lfsr;

  lfsr_galois dut (
    .clk(clk),
    .i_valid(i_valid),
    .i_rst(i_rst),
    .i_soft_reset(i_soft_reset),
    .i_seed(i_seed)
  );

  // 10MHz = 100ns

  always #50 clk = ~clk;

initial begin
    $dumpfile("tb/lfsr_galois_tb1.vcd");
    $dumpvars(0, lfsr_galois_tb1);
    
    clk = 0;
    i_valid = 0;
    i_rst = 0;
    i_soft_reset = 0;
    i_seed = 8'h00;

    async_reset;

    #1000;

    change_seed(8'hAA);
    
    soft_reset;

    #1000;

    random_valid;

    #1000;

    $finish;
end

  task async_reset;
    reg [7:0] random_reset;
    begin
      random_reset <= $urandom%100;  
      #10;
      $display("Numero: %0d", random_reset);
      i_rst = 1;
      #random_reset; 
      i_rst = 0;
    end
  endtask

  task soft_reset;
    reg [7:0] random_soft_reset;
    begin
      random_soft_reset <= $urandom%100; 
      #10; 
      $display("Numero: %0d", random_soft_reset);
      i_soft_reset = 1;
      #random_soft_reset;
      i_soft_reset = 0;
    end
  endtask

  task change_seed(input [7:0] seed_value);
    begin
      i_seed = seed_value;
      #10; 
    end
  endtask

  integer i;
  task random_valid;
    begin
      for (i = 0; i < 100; i = i + 1) begin
        i_valid = $random % 2; // 0 o 1
        #100; 
      end
    end
  endtask

endmodule

diseño-digital/LFSR/tb/lfsr_galois_tb1.vcd
$date
	Mon Aug 12 16:31:30 2024
$end
$version
	Icarus Verilog
$end
$timescale
	1ps
$end
$scope module lfsr_galois_tb1 $end
$var reg 1 ! clk $end
$var integer 32 " i [31:0] $end
$var reg 1 # i_rst $end
$var reg 8 $ i_seed [7:0] $end
$var reg 1 % i_soft_reset $end
$var reg 1 & i_valid $end
$scope module dut $end
$var wire 1 ' clk $end
$var wire 1 ( feedback $end
$var wire 1 ) i_rst $end
$var wire 8 * i_seed [7:0] $end
$var wire 1 + i_soft_reset $end
$var wire 1 , i_valid $end
$var wire 8 - o_lfsr [7:0] $end
$var reg 8 . lfsr_reg [7:0] $end
$var reg 8 / seed_reg [7:0] $end
$upscope $end
$scope task async_reset $end
$var reg 8 0 random_reset [7:0] $end
$upscope $end
$scope task change_seed $end
$var reg 8 1 seed_value [7:0] $end
$upscope $end
$scope task random_valid $end
$upscope $end
$scope task soft_reset $end
$var reg 8 2 random_soft_reset [7:0] $end
$upscope $end
$upscope $end
$enddefinitions $end
#0
$dumpvars
bx 2
bx 1
b1100000 0
b1 /
bx .
bx -
0,
0+
b0 *
0)
x(
0'
0&
0%
b0 $
0#
bx "
0!
$end
#10000
0(
b1 .
b1 -
1#
1)
#50000
1!
1'
#100000
0!
0'
#106000
0#
0)
#150000
1!
1'
#200000
0!
0'
#250000
1!
1'
#300000
0!
0'
#350000
1!
1'
#400000
0!
0'
#450000
1!
1'
#500000
0!
0'
#550000
1!
1'
#600000
0!
0'
#650000
1!
1'
#700000
0!
0'
#750000
1!
1'
#800000
0!
0'
#850000
1!
1'
#900000
0!
0'
#950000
1!
1'
#1000000
0!
0'
#1050000
1!
1'
#1100000
0!
0'
#1106000
b10101010 $
b10101010 *
b10101010 1
#1116000
b110001 2
#1126000
1%
1+
#1150000
1(
b10101010 .
b10101010 -
1!
1'
#1175000
0%
0+
#1200000
0!
0'
#1250000
1!
1'
#1300000
0!
0'
#1350000
1!
1'
#1400000
0!
0'
#1450000
1!
1'
#1500000
0!
0'
#1550000
1!
1'
#1600000
0!
0'
#1650000
1!
1'
#1700000
0!
0'
#1750000
1!
1'
#1800000
0!
0'
#1850000
1!
1'
#1900000
0!
0'
#1950000
1!
1'
#2000000
0!
0'
#2050000
1!
1'
#2100000
0!
0'
#2150000
1!
1'
#2175000
b0 "
#2200000
0!
0'
#2250000
1!
1'
#2275000
1&
1,
b1 "
#2300000
0!
0'
#2350000
0(
b1001001 .
b1001001 -
1!
1'
#2375000
b10 "
#2400000
0!
0'
#2450000
1(
b10010010 .
b10010010 -
1!
1'
#2475000
b11 "
#2500000
0!
0'
#2550000
0(
b111001 .
b111001 -
1!
1'
#2575000
b100 "
#2600000
0!
0'
#2650000
b1110010 .
b1110010 -
1!
1'
#2675000
b101 "
#2700000
0!
0'
#2750000
1(
b11100100 -
b11100100 .
1!
1'
#2775000
b110 "
#2800000
0!
0'
#2850000
b11010101 .
b11010101 -
1!
1'
#2875000
0&
0,
b111 "
#2900000
0!
0'
#2950000
1!
1'
#2975000
1&
1,
b1000 "
#3000000
0!
0'
#3050000
b10110111 -
b10110111 .
1!
1'
#3075000
b1001 "
#3100000
0!
0'
#3150000
0(
b1110011 -
b1110011 .
1!
1'
#3175000
0&
0,
b1010 "
#3200000
0!
0'
#3250000
1!
1'
#3275000
1&
1,
b1011 "
#3300000
0!
0'
#3350000
1(
b11100110 .
b11100110 -
1!
1'
#3375000
b1100 "
#3400000
0!
0'
#3450000
b11010001 .
b11010001 -
1!
1'
#3475000
0&
0,
b1101 "
#3500000
0!
0'
#3550000
1!
1'
#3575000
1&
1,
b1110 "
#3600000
0!
0'
#3650000
b10111111 -
b10111111 .
1!
1'
#3675000
0&
0,
b1111 "
#3700000
0!
0'
#3750000
1!
1'
#3775000
1&
1,
b10000 "
#3800000
0!
0'
#3850000
0(
b1100011 -
b1100011 .
1!
1'
#3875000
0&
0,
b10001 "
#3900000
0!
0'
#3950000
1!
1'
#3975000
1&
1,
b10010 "
#4000000
0!
0'
#4050000
1(
b11000110 .
b11000110 -
1!
1'
#4075000
b10011 "
#4100000
0!
0'
#4150000
b10010001 .
b10010001 -
1!
1'
#4175000
0&
0,
b10100 "
#4200000
0!
0'
#4250000
1!
1'
#4275000
1&
1,
b10101 "
#4300000
0!
0'
#4350000
0(
b111111 -
b111111 .
1!
1'
#4375000
0&
0,
b10110 "
#4400000
0!
0'
#4450000
1!
1'
#4475000
b10111 "
#4500000
0!
0'
#4550000
1!
1'
#4575000
b11000 "
#4600000
0!
0'
#4650000
1!
1'
#4675000
1&
1,
b11001 "
#4700000
0!
0'
#4750000
b1111110 .
b1111110 -
1!
1'
#4775000
0&
0,
b11010 "
#4800000
0!
0'
#4850000
1!
1'
#4875000
1&
1,
b11011 "
#4900000
0!
0'
#4950000
1(
b11111100 -
b11111100 .
1!
1'
#4975000
b11100 "
#5000000
0!
0'
#5050000
b11100101 .
b11100101 -
1!
1'
#5075000
b11101 "
#5100000
0!
0'
#5150000
b11010111 -
b11010111 .
1!
1'
#5175000
b11110 "
#5200000
0!
0'
#5250000
b10110011 -
b10110011 .
1!
1'
#5275000
0&
0,
b11111 "
#5300000
0!
0'
#5350000
1!
1'
#5375000
b100000 "
#5400000
0!
0'
#5450000
1!
1'
#5475000
b100001 "
#5500000
0!
0'
#5550000
1!
1'
#5575000
b100010 "
#5600000
0!
0'
#5650000
1!
1'
#5675000
1&
1,
b100011 "
#5700000
0!
0'
#5750000
0(
b1111011 -
b1111011 .
1!
1'
#5775000
0&
0,
b100100 "
#5800000
0!
0'
#5850000
1!
1'
#5875000
1&
1,
b100101 "
#5900000
0!
0'
#5950000
1(
b11110110 .
b11110110 -
1!
1'
#5975000
b100110 "
#6000000
0!
0'
#6050000
b11110001 .
b11110001 -
1!
1'
#6075000
b100111 "
#6100000
0!
0'
#6150000
b11111111 -
b11111111 .
1!
1'
#6175000
b101000 "
#6200000
0!
0'
#6250000
b11100011 -
b11100011 .
1!
1'
#6275000
b101001 "
#6300000
0!
0'
#6350000
b11011011 -
b11011011 .
1!
1'
#6375000
0&
0,
b101010 "
#6400000
0!
0'
#6450000
1!
1'
#6475000
b101011 "
#6500000
0!
0'
#6550000
1!
1'
#6575000
1&
1,
b101100 "
#6600000
0!
0'
#6650000
b10101011 -
b10101011 .
1!
1'
#6675000
b101101 "
#6700000
0!
0'
#6750000
0(
b1001011 -
b1001011 .
1!
1'
#6775000
b101110 "
#6800000
0!
0'
#6850000
1(
b10010110 .
b10010110 -
1!
1'
#6875000
0&
0,
b101111 "
#6900000
0!
0'
#6950000
1!
1'
#6975000
b110000 "
#7000000
0!
0'
#7050000
1!
1'
#7075000
b110001 "
#7100000
0!
0'
#7150000
1!
1'
#7175000
b110010 "
#7200000
0!
0'
#7250000
1!
1'
#7275000
b110011 "
#7300000
0!
0'
#7350000
1!
1'
#7375000
1&
1,
b110100 "
#7400000
0!
0'
#7450000
0(
b110001 .
b110001 -
1!
1'
#7475000
0&
0,
b110101 "
#7500000
0!
0'
#7550000
1!
1'
#7575000
b110110 "
#7600000
0!
0'
#7650000
1!
1'
#7675000
1&
1,
b110111 "
#7700000
0!
0'
#7750000
b1100010 .
b1100010 -
1!
1'
#7775000
b111000 "
#7800000
0!
0'
#7850000
1(
b11000100 -
b11000100 .
1!
1'
#7875000
0&
0,
b111001 "
#7900000
0!
0'
#7950000
1!
1'
#7975000
b111010 "
#8000000
0!
0'
#8050000
1!
1'
#8075000
b111011 "
#8100000
0!
0'
#8150000
1!
1'
#8175000
b111100 "
#8200000
0!
0'
#8250000
1!
1'
#8275000
b111101 "
#8300000
0!
0'
#8350000
1!
1'
#8375000
1&
1,
b111110 "
#8400000
0!
0'
#8450000
b10010101 .
b10010101 -
1!
1'
#8475000
b111111 "
#8500000
0!
0'
#8550000
0(
b110111 -
b110111 .
1!
1'
#8575000
b1000000 "
#8600000
0!
0'
#8650000
b1101110 .
b1101110 -
1!
1'
#8675000
b1000001 "
#8700000
0!
0'
#8750000
1(
b11011100 -
b11011100 .
1!
1'
#8775000
b1000010 "
#8800000
0!
0'
#8850000
b10100101 .
b10100101 -
1!
1'
#8875000
0&
0,
b1000011 "
#8900000
0!
0'
#8950000
1!
1'
#8975000
b1000100 "
#9000000
0!
0'
#9050000
1!
1'
#9075000
1&
1,
b1000101 "
#9100000
0!
0'
#9150000
0(
b1010111 -
b1010111 .
1!
1'
#9175000
b1000110 "
#9200000
0!
0'
#9250000
1(
b10101110 .
b10101110 -
1!
1'
#9275000
b1000111 "
#9300000
0!
0'
#9350000
0(
b1000001 .
b1000001 -
1!
1'
#9375000
0&
0,
b1001000 "
#9400000
0!
0'
#9450000
1!
1'
#9475000
b1001001 "
#9500000
0!
0'
#9550000
1!
1'
#9575000
1&
1,
b1001010 "
#9600000
0!
0'
#9650000
1(
b10000010 .
b10000010 -
1!
1'
#9675000
b1001011 "
#9700000
0!
0'
#9750000
0(
b11001 .
b11001 -
1!
1'
#9775000
0&
0,
b1001100 "
#9800000
0!
0'
#9850000
1!
1'
#9875000
1&
1,
b1001101 "
#9900000
0!
0'
#9950000
b110010 .
b110010 -
1!
1'
#9975000
b1001110 "
#10000000
0!
0'
#10050000
b1100100 -
b1100100 .
1!
1'
#10075000
0&
0,
b1001111 "
#10100000
0!
0'
#10150000
1!
1'
#10175000
1&
1,
b1010000 "
#10200000
0!
0'
#10250000
1(
b11001000 -
b11001000 .
1!
1'
#10275000
b1010001 "
#10300000
0!
0'
#10350000
b10001101 .
b10001101 -
1!
1'
#10375000
b1010010 "
#10400000
0!
0'
#10450000
0(
b111 -
b111 .
1!
1'
#10475000
0&
0,
b1010011 "
#10500000
0!
0'
#10550000
1!
1'
#10575000
1&
1,
b1010100 "
#10600000
0!
0'
#10650000
b1110 .
b1110 -
1!
1'
#10675000
b1010101 "
#10700000
0!
0'
#10750000
b11100 -
b11100 .
1!
1'
#10775000
0&
0,
b1010110 "
#10800000
0!
0'
#10850000
1!
1'
#10875000
b1010111 "
#10900000
0!
0'
#10950000
1!
1'
#10975000
b1011000 "
#11000000
0!
0'
#11050000
1!
1'
#11075000
b1011001 "
#11100000
0!
0'
#11150000
1!
1'
#11175000
1&
1,
b1011010 "
#11200000
0!
0'
#11250000
b111000 -
b111000 .
1!
1'
#11275000
b1011011 "
#11300000
0!
0'
#11350000
b1110000 -
b1110000 .
1!
1'
#11375000
0&
0,
b1011100 "
#11400000
0!
0'
#11450000
1!
1'
#11475000
b1011101 "
#11500000
0!
0'
#11550000
1!
1'
#11575000
1&
1,
b1011110 "
#11600000
0!
0'
#11650000
1(
b11100000 -
b11100000 .
1!
1'
#11675000
b1011111 "
#11700000
0!
0'
#11750000
b11011101 .
b11011101 -
1!
1'
#11775000
b1100000 "
#11800000
0!
0'
#11850000
b10100111 -
b10100111 .
1!
1'
#11875000
b1100001 "
#11900000
0!
0'
#11950000
0(
b1010011 -
b1010011 .
1!
1'
#11975000
b1100010 "
#12000000
0!
0'
#12050000
1(
b10100110 .
b10100110 -
1!
1'
#12075000
0&
0,
b1100011 "
#12100000
0!
0'
#12150000
1!
1'
#12175000
b1100100 "
