diseño-digital/LFSR/lfsr_checker.v
module lfsr_checker(
  input  wire         clk,        
  input  wire         i_rst,      
  input  wire  [7:0]  i_lfsr,
  input  wire  [7:0]  i_seed_reg, 
  output wire         o_lock   
);

  reg [7:0] expected_lfsr;

  reg [2:0] valid_count;
  reg [1:0] invalid_count;

  reg lock;

  wire feedback = expected_lfsr[7] ^ (expected_lfsr[6:0] == 7'b0000000);
  wire i_feedback = i_lfsr[7] ^ (i_lfsr[6:0] == 7'b0000000);

  always @(posedge clk or posedge i_rst) begin
    if (i_rst) begin

      expected_lfsr <= i_seed_reg;
      lock          <= 0;
      valid_count   <= 0;
      invalid_count <= 0;

    end else begin

      if (i_lfsr == expected_lfsr) begin
      
      expected_lfsr[0] <= feedback;
      expected_lfsr[1] <= expected_lfsr[0];
      expected_lfsr[2] <= expected_lfsr[1] ^ feedback;
      expected_lfsr[3] <= expected_lfsr[2] ^ feedback;
      expected_lfsr[4] <= expected_lfsr[3] ^ feedback;
      expected_lfsr[5] <= expected_lfsr[4];
      expected_lfsr[6] <= expected_lfsr[5];
      expected_lfsr[7] <= expected_lfsr[6];

      valid_count <= valid_count + 1;
      invalid_count <= 0;

      if (valid_count >= 5) begin
        lock <= 1'b1;
      end

      end else begin

        expected_lfsr[0] <= i_feedback;
        expected_lfsr[1] <= i_lfsr[0];
        expected_lfsr[2] <= i_lfsr[1] ^ i_feedback;
        expected_lfsr[3] <= i_lfsr[2] ^ i_feedback;
        expected_lfsr[4] <= i_lfsr[3] ^ i_feedback;
        expected_lfsr[5] <= i_lfsr[4];
        expected_lfsr[6] <= i_lfsr[5];
        expected_lfsr[7] <= i_lfsr[6];

        invalid_count <= invalid_count + 1;
        valid_count <= 0;
        
        if (invalid_count >= 3) begin
          lock <= 1'b0;
        end

      end

    end
  end

  assign o_lock = lock;

endmodule

diseño-digital/LFSR/lfsr_galois.v
`include "lfsr_checker.v"
`include "lfsr_checker_2.v"

module lfsr_galois(
  input   wire        clk,          // Reloj del sistema
  input   wire        i_valid,      // Señal de validación para generar nueva secuencia
  input   wire        i_rst,        // Reset asincrónico para inicializar con la semilla fija
  input   wire        i_soft_reset, // Reset sincrónico para inicializar con la semilla del puerto
  input   wire [7:0]  i_seed,       // Semilla inicial proporcionada desde el puerto
  output  wire [7:0]  o_lfsr,       // Salida de la secuencia generada
  output  wire        o_lock        // Señal de bloqueo del checker
);

// Registro para el estado actual del LFSR
reg [7:0] lfsr_reg;

// Registro para la semilla fija
reg [7:0] seed_reg = 8'b00000001;

// Feedback del LFSR
wire feedback = lfsr_reg[7] ^ (lfsr_reg[6:0]==7'b0000000);

always @(posedge clk or posedge i_rst) begin

  if(i_rst) begin

    lfsr_reg <= seed_reg;

  end else if(i_soft_reset) begin

    lfsr_reg <= i_seed;

  end else if(i_valid) begin

    lfsr_reg[0] <= feedback;
    lfsr_reg[1] <= lfsr_reg[0];
    lfsr_reg[2] <= lfsr_reg[1]^feedback;
    lfsr_reg[3] <= lfsr_reg[2]^feedback;
    lfsr_reg[4] <= lfsr_reg[3]^feedback;
    lfsr_reg[5] <= lfsr_reg[4];
    lfsr_reg[6] <= lfsr_reg[5];
    lfsr_reg[7] <= lfsr_reg[6];

  end

end

assign o_lfsr = lfsr_reg;

lfsr_checker u_lfsr_checker(
    .clk(clk),
    .i_rst(i_rst),
    .i_lfsr(o_lfsr),
    .i_seed_reg(seed_reg),   
    .o_lock(o_lock)
  );

endmodule

diseño-digital/LFSR/tb/lfsr_galois_tb1.v
`timescale 1ns / 1ps
`include "lfsr_galois.v"

//-----------------------------------------------------
//iverilog -o tb/tb1 tb/lfsr_galois_tb1.v
//vvp tb/tb1
//-----------------------------------------------------

module lfsr_galois_tb1;

  reg clk;
  reg i_valid;
  reg i_rst;
  reg i_soft_reset;
  reg [7:0] i_seed;
  wire [7:0] o_lfsr;

  lfsr_galois dut (
    .clk(clk),
    .i_valid(i_valid),
    .i_rst(i_rst),
    .i_soft_reset(i_soft_reset),
    .i_seed(i_seed)
  );

  // 10MHz = 100ns

  always #50 clk = ~clk;

initial begin
    $dumpfile("tb/lfsr_galois_tb1.vcd");
    $dumpvars(0, lfsr_galois_tb1);
    
    clk = 0;
    i_valid = 0;
    i_rst = 0;
    i_soft_reset = 0;
    i_seed = 8'h00;

    async_reset;

    #1000;

    change_seed(8'hAA);
    
    soft_reset;

    #1000;

    random_valid;

    #1000;

    $finish;
end

  task async_reset;
    reg [7:0] random_reset;
    begin
      random_reset <= $urandom%100;  
      #10;
      $display("Numero: %0d", random_reset);
      i_rst = 1;
      #random_reset; 
      i_rst = 0;
    end
  endtask

  task soft_reset;
    reg [7:0] random_soft_reset;
    begin
      random_soft_reset <= $urandom%100; 
      #10; 
      $display("Numero: %0d", random_soft_reset);
      i_soft_reset = 1;
      #random_soft_reset;
      i_soft_reset = 0;
    end
  endtask

  task change_seed(input [7:0] seed_value);
    begin
      i_seed = seed_value;
      #10; 
    end
  endtask

  integer i;
  task random_valid;
    begin
      for (i = 0; i < 100; i = i + 1) begin
        i_valid = $random % 2; // 0 o 1
        #100; 
      end
    end
  endtask

endmodule

diseño-digital/LFSR/tb/lfsr_galois_tb1.vcd
$date
	Fri Aug 23 11:21:20 2024
$end
$version
	Icarus Verilog
$end
$timescale
	1ps
$end
$scope module lfsr_galois_tb1 $end
$var wire 8 ! o_lfsr [7:0] $end
$var reg 1 " clk $end
$var integer 32 # i [31:0] $end
$var reg 1 $ i_rst $end
$var reg 8 % i_seed [7:0] $end
$var reg 1 & i_soft_reset $end
$var reg 1 ' i_valid $end
$scope module dut $end
$var wire 1 ( clk $end
$var wire 1 ) feedback $end
$var wire 1 * i_rst $end
$var wire 8 + i_seed [7:0] $end
$var wire 1 , i_soft_reset $end
$var wire 1 - i_valid $end
$var wire 8 . o_lfsr [7:0] $end
$var wire 1 / o_lock $end
$var reg 8 0 lfsr_reg [7:0] $end
$var reg 8 1 seed_reg [7:0] $end
$scope module u_lfsr_checker $end
$var wire 1 ( clk $end
$var wire 1 2 feedback $end
$var wire 1 3 i_feedback $end
$var wire 8 4 i_lfsr [7:0] $end
$var wire 1 * i_rst $end
$var wire 8 5 i_seed_reg [7:0] $end
$var wire 1 / o_lock $end
$var reg 8 6 expected_lfsr [7:0] $end
$var reg 2 7 invalid_count [1:0] $end
$var reg 1 8 lock $end
$var reg 3 9 valid_count [2:0] $end
$upscope $end
$upscope $end
$scope task async_reset $end
$var reg 8 : random_reset [7:0] $end
$upscope $end
$scope task change_seed $end
$var reg 8 ; seed_value [7:0] $end
$upscope $end
$scope task random_valid $end
$upscope $end
$scope task soft_reset $end
$var reg 8 < random_soft_reset [7:0] $end
$upscope $end
$upscope $end
$enddefinitions $end
#0
$dumpvars
bx <
bx ;
b1110110 :
bx 9
x8
bx 7
bx 6
b1 5
bx 4
x3
x2
b1 1
bx 0
x/
bx .
0-
0,
b0 +
0*
x)
0(
0'
0&
b0 %
0$
bx #
0"
bx !
$end
#10000
02
0)
03
b0 7
b0 9
08
0/
b1 6
b1 0
b1 !
b1 .
b1 4
1$
1*
#50000
1"
1(
#100000
0"
0(
#150000
b1 9
b10 6
0$
0*
1"
1(
#200000
0"
0(
#250000
b0 9
b1 7
b10 6
1"
1(
#300000
0"
0(
#350000
b10 7
b10 6
1"
1(
#400000
0"
0(
#450000
b11 7
b10 6
1"
1(
#500000
0"
0(
#550000
b0 7
b10 6
1"
1(
#600000
0"
0(
#650000
b1 7
b10 6
1"
1(
#700000
0"
0(
#750000
b10 7
b10 6
1"
1(
#800000
0"
0(
#850000
b11 7
b10 6
1"
1(
#900000
0"
0(
#950000
b0 7
b10 6
1"
1(
#1000000
0"
0(
#1050000
b1 7
b10 6
1"
1(
#1100000
0"
0(
#1150000
b10 7
b10 6
1"
1(
b10101010 %
b10101010 +
b10101010 ;
#1160000
b11111001 <
#1170000
1&
1,
#1200000
0"
0(
#1250000
1)
13
b10101010 0
b10101010 !
b10101010 .
b10101010 4
b11 7
b10 6
1"
1(
#1300000
0"
0(
#1350000
b0 7
b1001001 6
1"
1(
#1400000
0"
0(
#1450000
b1 7
b1001001 6
0&
0,
1"
1(
#1500000
0"
0(
#1550000
b10 7
b1001001 6
1"
1(
#1600000
0"
0(
#1650000
b11 7
b1001001 6
1"
1(
#1700000
0"
0(
#1750000
b0 7
b1001001 6
1"
1(
#1800000
0"
0(
#1850000
b1 7
b1001001 6
1"
1(
#1900000
0"
0(
#1950000
b10 7
b1001001 6
1"
1(
#2000000
0"
0(
#2050000
b11 7
b1001001 6
1"
1(
#2100000
0"
0(
#2150000
b0 7
b1001001 6
1"
1(
#2200000
0"
0(
#2250000
b1 7
b1001001 6
1"
1(
#2300000
0"
0(
#2350000
b10 7
b1001001 6
1"
1(
#2400000
0"
0(
#2450000
b11 7
b1001001 6
1"
1(
b0 #
#2500000
0"
0(
#2550000
0)
03
b0 7
b1001001 6
b1001001 0
b1001001 !
b1001001 .
b1001001 4
1'
1-
1"
1(
b1 #
#2600000
0"
0(
#2650000
1)
13
12
b10010010 0
b10010010 !
b10010010 .
b10010010 4
b1 9
b10010010 6
1"
1(
b10 #
#2700000
0"
0(
#2750000
02
0)
03
b10 9
b111001 6
b111001 0
b111001 !
b111001 .
b111001 4
1"
1(
b11 #
#2800000
0"
0(
#2850000
b1110010 0
b1110010 !
b1110010 .
b1110010 4
b11 9
b1110010 6
1"
1(
b100 #
#2900000
0"
0(
#2950000
12
1)
13
b100 9
b11100100 6
b11100100 !
b11100100 .
b11100100 4
b11100100 0
1"
1(
b101 #
#3000000
0"
0(
#3050000
b11010101 0
b11010101 !
b11010101 .
b11010101 4
b101 9
b11010101 6
1"
1(
b110 #
#3100000
0"
0(
#3150000
18
1/
b110 9
b10110111 6
0'
0-
1"
1(
b111 #
#3200000
0"
0(
#3250000
b10110111 !
b10110111 .
b10110111 4
b10110111 0
b0 9
b1 7
b10110111 6
1'
1-
1"
1(
b1000 #
#3300000
0"
0(
#3350000
02
0)
03
b0 7
b1 9
b1110011 6
b1110011 !
b1110011 .
b1110011 4
b1110011 0
1"
1(
b1001 #
#3400000
0"
0(
#3450000
12
b10 9
b11100110 6
0'
0-
1"
1(
b1010 #
#3500000
0"
0(
#3550000
1)
13
b0 9
b1 7
b11100110 6
b11100110 0
b11100110 !
b11100110 .
b11100110 4
1'
1-
1"
1(
b1011 #
#3600000
0"
0(
#3650000
b11010001 0
b11010001 !
b11010001 .
b11010001 4
b0 7
b1 9
b11010001 6
1"
1(
b1100 #
#3700000
0"
0(
#3750000
b10 9
b10111111 6
0'
0-
1"
1(
b1101 #
#3800000
0"
0(
#3850000
b10111111 !
b10111111 .
b10111111 4
b10111111 0
b0 9
b1 7
b10111111 6
1'
1-
1"
1(
b1110 #
#3900000
0"
0(
#3950000
02
b0 7
b1 9
b1100011 6
0'
0-
1"
1(
b1111 #
#4000000
0"
0(
#4050000
0)
03
b1100011 !
b1100011 .
b1100011 4
b1100011 0
b0 9
b1 7
b1100011 6
1'
1-
1"
1(
b10000 #
#4100000
0"
0(
#4150000
12
b0 7
b1 9
b11000110 6
0'
0-
1"
1(
b10001 #
#4200000
0"
0(
#4250000
1)
13
b11000110 0
b11000110 !
b11000110 .
b11000110 4
b0 9
b1 7
b11000110 6
1'
1-
1"
1(
b10010 #
#4300000
0"
0(
#4350000
b0 7
b1 9
b10010001 6
b10010001 0
b10010001 !
b10010001 .
b10010001 4
1"
1(
b10011 #
#4400000
0"
0(
#4450000
02
b10 9
b111111 6
0'
0-
1"
1(
b10100 #
#4500000
0"
0(
#4550000
0)
03
b0 9
b1 7
b111111 6
b111111 !
b111111 .
b111111 4
b111111 0
1'
1-
1"
1(
b10101 #
#4600000
0"
0(
#4650000
b0 7
b1 9
b1111110 6
0'
0-
1"
1(
b10110 #
#4700000
0"
0(
#4750000
b0 9
b1 7
b1111110 6
1"
1(
b10111 #
#4800000
0"
0(
#4850000
b10 7
b1111110 6
1"
1(
b11000 #
#4900000
0"
0(
#4950000
b11 7
b1111110 6
b1111110 0
b1111110 !
b1111110 .
b1111110 4
1'
1-
1"
1(
b11001 #
#5000000
0"
0(
#5050000
12
b0 7
b1 9
b11111100 6
0'
0-
1"
1(
b11010 #
#5100000
0"
0(
#5150000
1)
13
b0 9
b1 7
b11111100 6
b11111100 !
b11111100 .
b11111100 4
b11111100 0
1'
1-
1"
1(
b11011 #
#5200000
0"
0(
#5250000
b11100101 0
b11100101 !
b11100101 .
b11100101 4
b0 7
b1 9
b11100101 6
1"
1(
b11100 #
#5300000
0"
0(
#5350000
b10 9
b11010111 6
b11010111 !
b11010111 .
b11010111 4
b11010111 0
1"
1(
b11101 #
#5400000
0"
0(
#5450000
b10110011 !
b10110011 .
b10110011 4
b10110011 0
b11 9
b10110011 6
1"
1(
b11110 #
#5500000
0"
0(
#5550000
02
b100 9
b1111011 6
0'
0-
1"
1(
b11111 #
#5600000
0"
0(
#5650000
b0 9
b1 7
b1111011 6
1"
1(
b100000 #
#5700000
0"
0(
#5750000
b10 7
b1111011 6
1"
1(
b100001 #
#5800000
0"
0(
#5850000
b11 7
b1111011 6
1"
1(
b100010 #
#5900000
0"
0(
#5950000
0)
03
08
0/
b0 7
b1111011 6
b1111011 !
b1111011 .
b1111011 4
b1111011 0
1'
1-
1"
1(
b100011 #
#6000000
0"
0(
#6050000
12
b1 9
b11110110 6
0'
0-
1"
1(
b100100 #
#6100000
0"
0(
#6150000
1)
13
b0 9
b1 7
b11110110 6
b11110110 0
b11110110 !
b11110110 .
b11110110 4
1'
1-
1"
1(
b100101 #
#6200000
0"
0(
#6250000
b11110001 0
b11110001 !
b11110001 .
b11110001 4
b0 7
b1 9
b11110001 6
1"
1(
b100110 #
#6300000
0"
0(
#6350000
b10 9
b11111111 6
b11111111 !
b11111111 .
b11111111 4
b11111111 0
1"
1(
b100111 #
#6400000
0"
0(
#6450000
b11100011 !
b11100011 .
b11100011 4
b11100011 0
b11 9
b11100011 6
1"
1(
b101000 #
#6500000
0"
0(
#6550000
b100 9
b11011011 6
b11011011 !
b11011011 .
b11011011 4
b11011011 0
1"
1(
b101001 #
#6600000
0"
0(
#6650000
b101 9
b10101011 6
0'
0-
1"
1(
b101010 #
#6700000
0"
0(
#6750000
b0 9
b1 7
b10101011 6
1"
1(
b101011 #
#6800000
0"
0(
#6850000
b10101011 !
b10101011 .
b10101011 4
b10101011 0
b10 7
b10101011 6
1'
1-
1"
1(
b101100 #
#6900000
0"
0(
#6950000
02
0)
03
b0 7
b1 9
b1001011 6
b1001011 !
b1001011 .
b1001011 4
b1001011 0
1"
1(
b101101 #
#7000000
0"
0(
#7050000
1)
13
12
b10010110 0
b10010110 !
b10010110 .
b10010110 4
b10 9
b10010110 6
1"
1(
b101110 #
#7100000
0"
0(
#7150000
02
b11 9
b110001 6
0'
0-
1"
1(
b101111 #
#7200000
0"
0(
#7250000
b0 9
b1 7
b110001 6
1"
1(
b110000 #
#7300000
0"
0(
#7350000
b10 7
b110001 6
1"
1(
b110001 #
#7400000
0"
0(
#7450000
b11 7
b110001 6
1"
1(
b110010 #
#7500000
0"
0(
#7550000
b0 7
b110001 6
1"
1(
b110011 #
#7600000
0"
0(
#7650000
0)
03
b110001 0
b110001 !
b110001 .
b110001 4
b1 7
b110001 6
1'
1-
1"
1(
b110100 #
#7700000
0"
0(
#7750000
b0 7
b1 9
b1100010 6
0'
0-
1"
1(
b110101 #
#7800000
0"
0(
#7850000
b0 9
b1 7
b1100010 6
1"
1(
b110110 #
#7900000
0"
0(
#7950000
b10 7
b1100010 6
b1100010 0
b1100010 !
b1100010 .
b1100010 4
1'
1-
1"
1(
b110111 #
#8000000
0"
0(
#8050000
1)
13
12
b11000100 !
b11000100 .
b11000100 4
b11000100 0
b0 7
b1 9
b11000100 6
1"
1(
b111000 #
#8100000
0"
0(
#8150000
b10 9
b10010101 6
0'
0-
1"
1(
b111001 #
#8200000
0"
0(
#8250000
b0 9
b1 7
b10010101 6
1"
1(
b111010 #
#8300000
0"
0(
#8350000
b10 7
b10010101 6
1"
1(
b111011 #
#8400000
0"
0(
#8450000
b11 7
b10010101 6
1"
1(
b111100 #
#8500000
0"
0(
#8550000
b0 7
b10010101 6
1"
1(
b111101 #
#8600000
0"
0(
#8650000
b10010101 0
b10010101 !
b10010101 .
b10010101 4
b1 7
b10010101 6
1'
1-
1"
1(
b111110 #
#8700000
0"
0(
#8750000
02
0)
03
b0 7
b1 9
b110111 6
b110111 !
b110111 .
b110111 4
b110111 0
1"
1(
b111111 #
#8800000
0"
0(
#8850000
b1101110 0
b1101110 !
b1101110 .
b1101110 4
b10 9
b1101110 6
1"
1(
b1000000 #
#8900000
0"
0(
#8950000
12
1)
13
b11 9
b11011100 6
b11011100 !
b11011100 .
b11011100 4
b11011100 0
1"
1(
b1000001 #
#9000000
0"
0(
#9050000
b10100101 0
b10100101 !
b10100101 .
b10100101 4
b100 9
b10100101 6
1"
1(
b1000010 #
#9100000
0"
0(
#9150000
02
b101 9
b1010111 6
0'
0-
1"
1(
b1000011 #
#9200000
0"
0(
#9250000
b0 9
b1 7
b1010111 6
1"
1(
b1000100 #
#9300000
0"
0(
#9350000
0)
03
b10 7
b1010111 6
b1010111 !
b1010111 .
b1010111 4
b1010111 0
1'
1-
1"
1(
b1000101 #
#9400000
0"
0(
#9450000
1)
13
12
b10101110 0
b10101110 !
b10101110 .
b10101110 4
b0 7
b1 9
b10101110 6
1"
1(
b1000110 #
#9500000
0"
0(
#9550000
02
0)
03
b10 9
b1000001 6
b1000001 0
b1000001 !
b1000001 .
b1000001 4
1"
1(
b1000111 #
#9600000
0"
0(
#9650000
12
b11 9
b10000010 6
0'
0-
1"
1(
b1001000 #
#9700000
0"
0(
#9750000
b0 9
b1 7
b10000010 6
1"
1(
b1001001 #
#9800000
0"
0(
#9850000
1)
13
b10000010 0
b10000010 !
b10000010 .
b10000010 4
b10 7
b10000010 6
1'
1-
1"
1(
b1001010 #
#9900000
0"
0(
#9950000
02
0)
03
b0 7
b1 9
b11001 6
b11001 0
b11001 !
b11001 .
b11001 4
1"
1(
b1001011 #
#10000000
0"
0(
#10050000
b10 9
b110010 6
0'
0-
1"
1(
b1001100 #
#10100000
0"
0(
#10150000
b0 9
b1 7
b110010 6
b110010 0
b110010 !
b110010 .
b110010 4
1'
1-
1"
1(
b1001101 #
#10200000
0"
0(
#10250000
b1100100 !
b1100100 .
b1100100 4
b1100100 0
b0 7
b1 9
b1100100 6
1"
1(
b1001110 #
#10300000
0"
0(
#10350000
12
b10 9
b11001000 6
0'
0-
1"
1(
b1001111 #
#10400000
0"
0(
#10450000
1)
13
b11001000 !
b11001000 .
b11001000 4
b11001000 0
b0 9
b1 7
b11001000 6
1'
1-
1"
1(
b1010000 #
#10500000
0"
0(
#10550000
b0 7
b1 9
b10001101 6
b10001101 0
b10001101 !
b10001101 .
b10001101 4
1"
1(
b1010001 #
#10600000
0"
0(
#10650000
0)
03
02
b111 !
b111 .
b111 4
b111 0
b10 9
b111 6
1"
1(
b1010010 #
#10700000
0"
0(
#10750000
b11 9
b1110 6
0'
0-
1"
1(
b1010011 #
#10800000
0"
0(
#10850000
b1110 0
b1110 !
b1110 .
b1110 4
b0 9
b1 7
b1110 6
1'
1-
1"
1(
b1010100 #
#10900000
0"
0(
#10950000
b0 7
b1 9
b11100 6
b11100 !
b11100 .
b11100 4
b11100 0
1"
1(
b1010101 #
#11000000
0"
0(
#11050000
b10 9
b111000 6
0'
0-
1"
1(
b1010110 #
#11100000
0"
0(
#11150000
b0 9
b1 7
b111000 6
1"
1(
b1010111 #
#11200000
0"
0(
#11250000
b10 7
b111000 6
1"
1(
b1011000 #
#11300000
0"
0(
#11350000
b11 7
b111000 6
1"
1(
b1011001 #
#11400000
0"
0(
#11450000
b111000 !
b111000 .
b111000 4
b111000 0
b0 7
b111000 6
1'
1-
1"
1(
b1011010 #
#11500000
0"
0(
#11550000
b1 9
b1110000 6
b1110000 !
b1110000 .
b1110000 4
b1110000 0
1"
1(
b1011011 #
#11600000
0"
0(
#11650000
12
b10 9
b11100000 6
0'
0-
1"
1(
b1011100 #
#11700000
0"
0(
#11750000
b0 9
b1 7
b11100000 6
1"
1(
b1011101 #
#11800000
0"
0(
#11850000
1)
13
b11100000 !
b11100000 .
b11100000 4
b11100000 0
b10 7
b11100000 6
1'
1-
1"
1(
b1011110 #
#11900000
0"
0(
#11950000
b0 7
b1 9
b11011101 6
b11011101 0
b11011101 !
b11011101 .
b11011101 4
1"
1(
b1011111 #
#12000000
0"
0(
#12050000
b10100111 !
b10100111 .
b10100111 4
b10100111 0
b10 9
b10100111 6
1"
1(
b1100000 #
#12100000
0"
0(
#12150000
02
0)
03
b11 9
b1010011 6
b1010011 !
b1010011 .
b1010011 4
b1010011 0
1"
1(
b1100001 #
#12200000
0"
0(
#12250000
1)
13
12
b10100110 0
b10100110 !
b10100110 .
b10100110 4
b100 9
b10100110 6
1"
1(
b1100010 #
#12300000
0"
0(
#12350000
02
b101 9
b1010001 6
0'
0-
1"
1(
b1100011 #
#12400000
0"
0(
#12450000
b0 9
b1 7
b1010001 6
1"
1(
b1100100 #
#12500000
0"
0(
#12550000
b10 7
b1010001 6
1"
1(
#12600000
0"
0(
#12650000
b11 7
b1010001 6
1"
1(
#12700000
0"
0(
#12750000
b0 7
b1010001 6
1"
1(
#12800000
0"
0(
#12850000
b1 7
b1010001 6
1"
1(
#12900000
0"
0(
#12950000
b10 7
b1010001 6
1"
1(
#13000000
0"
0(
#13050000
b11 7
b1010001 6
1"
1(
#13100000
0"
0(
#13150000
b0 7
b1010001 6
1"
1(
#13200000
0"
0(
#13250000
b1 7
b1010001 6
1"
1(
#13300000
0"
0(
#13350000
b10 7
b1010001 6
1"
1(
#13400000
0"
0(
#13450000
b11 7
b1010001 6
1"
1(
