tutorial-verilog/3/blocking_nonblocking.v
module blocking_nonblocking();

reg a,b,c,d;
// Blocking Assignment
initial begin
  #10 a = 0;
  #11 a = 1;
  #12 a = 0;
  #13 a = 1;
end

initial begin
  #10 b <= 0;
  #11 b <= 1;
  #12 b <= 0;
  #13 b <= 1;
end

initial begin
   c = #10 0;
   c = #11 1;
   c = #12 0;
   c = #13 1;
end

initial begin
   d <= #10 0;
   d <= #11 1;
   d <= #12 0;
   d <= #13 1;
end

initial begin
  $dumpfile("blocking_nonblocking.vcd");
    $dumpvars(0, blocking_nonblocking);  
  $monitor("TIME = %g A = %b B = %b C = %b D = %b",$time, a, b, c, d);
  #50 $finish;
end

endmodule

3/blocking_nonblocking.vcd
$date
	Mon Apr 08 15:08:49 2024
$end
$version
	Icarus Verilog
$end
$timescale
	1s
$end
$scope module blocking_nonblocking $end
$var reg 1 ! a $end
$var reg 1 " b $end
$var reg 1 # c $end
$var reg 1 $ d $end
$upscope $end
$enddefinitions $end
#0
$dumpvars
x$
x#
x"
x!
$end
#10
0"
0$
0#
0!
#11
1$
#12
0$
#13
1$
#21
1"
1#
1!
#33
0"
0#
0!
#46
1"
1#
1!
