diseño-digital/prender-leds/shiftreg.v

module shiftreg
    #(
        parameter NB_LEDS = 4
    )
    (
        output [NB_LEDS - 1 : 0] o_led  ,
        input                    i_valid,
        input                    i_reset,
        input                    clock
    );

    // Vars
    reg [NB_LEDS - 1 : 0] shiftRegister;

    integer ptr;

    always @(posedge clock) begin
        if(i_reset) begin
            shiftRegister <= {{NB_LEDS-1{1'b0}},1'b1};
        end
        else if (i_valid) begin
            // // Option 1
            // shiftRegister[1] <= shiftRegister[0];
            // shiftRegister[2] <= shiftRegister[1];
            // shiftRegister[3] <= shiftRegister[2];
            // shiftRegister[0] <= shiftRegister[3];

            // // Option 2
            // for(ptr=0;ptr<NB_LEDS-1;ptr=ptr+1)begin
            //     shiftRegister[ptr+1] <= shiftRegister[ptr];
            // end
            // shiftRegister[0] <= shiftRegister[NB_LEDS-1];

            // // Option 3
            // shiftRegister <= shiftRegister << 1;
            // shiftRegister[0] <= shiftRegister[NB_LEDS-1];

            // Option 4
            shiftRegister <= {shiftRegister[NB_LEDS-2:0],shiftRegister[NB_LEDS-1]};
        end
        else begin
            shiftRegister <= shiftRegister;
        end
            
    end

    assign o_led = shiftRegister;
    
endmodule

diseño-digital/prender-leds/count.v

module count 
    #(
        parameter NB_SW      = 3,
        parameter NB_COUNTER = 32
    )    
    (
        output                o_valid,
        input [NB_SW - 1 : 0] i_sw   ,
        input                 i_reset,
        input                 clock
    );
    
    // Localparam
    localparam R0 = (2**(NB_COUNTER-10))-1;
    localparam R1 = (2**(NB_COUNTER-11))-1;
    localparam R2 = (2**(NB_COUNTER-12))-1;
    localparam R3 = (2**(NB_COUNTER-13))-1;

    // Var
    /*wire [NB_COUNTER - 1 : 0] limit_ref;

    assign limit_ref =  (i_sw[2:1]==2'b00) ? R0 :
                        (i_sw[2:1]==2'b01) ? R1 :
                        (i_sw[2:1]==2'b10) ? R2 : R3;
    */  

    reg [NB_COUNTER - 1 : 0] limit_ref;

    always @(*) begin
         if(i_sw[2:1]==2'b00)
             limit_ref = R0;
         else if(i_sw[2:1]==2'b01)
             limit_ref = R1;
         else if(i_sw[2:1]==2'b10)
             limit_ref = R2;
         else 
             limit_ref = R3;
    end
    
    // always @(*) begin
    //     case (i_sw[2:1])
    //         2'b00: limit_ref = R0;
    //         2'b01: limit_ref = R1;
    //         2'b10: limit_ref = R2;
    //         2'b11: limit_ref = R3;
    //     endcase
    // end

    reg [NB_COUNTER - 1 : 0] counter;
    reg                      valid;

    always @(posedge clock) begin
        if(i_reset) begin
            counter <= {NB_COUNTER{1'b0}}; //0 / 'd0;
            valid   <= 1'b0;
        end
        else if (i_sw[0]) begin
            
            if(counter >= limit_ref)begin
                counter <= {NB_COUNTER{1'b0}};
                valid   <= 1'b1;
            end
            else begin
                counter <= counter + {{NB_COUNTER-1{1'b0}},1'b1}; //'d1;
                valid   <= 1'b0;
            end

        end
        else begin
            counter <= counter;
            valid   <= valid;
        end

    end

    assign o_valid = valid;
    

endmodule

diseño-digital/prender-leds/top.v
`include "count.v"
`include "shiftreg.v"

module top 
    #(
        parameter NB_LEDS    = 4,
        parameter NB_SW      = 4,
        parameter NB_COUNTER = 32
    )
    (
        output [NB_LEDS - 1 : 0] o_led  ,
        output [NB_LEDS - 1 : 0] o_led_b,
        output [NB_LEDS - 1 : 0] o_leg_g,
        input  [NB_SW   - 1 : 0] i_sw   ,
        input                    i_reset,
        input                    clock     
    );

    wire                   connect_c2sr;
    wire [NB_LEDS - 1 : 0] connect_leds;

    count 
        #(
            .NB_SW      (NB_SW-1   ),
            .NB_COUNTER (NB_COUNTER)
        )
        u_count
        (
            .o_valid (connect_c2sr      ),
            .i_sw    (i_sw[NB_SW-2:0]   ),
            .i_reset (i_reset           ),
            .clock   (clock             )
        );
    
    shiftreg
        #(
            .NB_LEDS (NB_LEDS)
        )
        u_shiftreg
        (
            .o_led   (connect_leds),
            .i_valid (connect_c2sr),
            .i_reset (i_reset     ),
            .clock   (clock       )
        );
        

        assign o_led   = connect_leds;
        assign o_led_b = (i_sw[NB_SW-1]==1'b1) ? connect_leds : 'b0         ;
        assign o_leg_g = (i_sw[NB_SW-1]==1'b1) ? 'b0          : connect_leds;

endmodule

diseño-digital/prender-leds/tb/tb1.v
`timescale 1ns / 1ps
`include "top.v"

//iverilog -o tb/tb1 tb/tb1.v
//vvp tb/tb1

module tb1;

    //Parametros
    parameter NB_LEDS    = 4;
    parameter NB_SW      = 4;
    parameter NB_COUNTER = 14;

    reg [NB_SW-1:0] i_sw;
    reg i_reset;
    reg clock;
    wire [NB_LEDS-1:0] o_led, o_led_b, o_led_g;

    top
        #(
            .NB_LEDS    (NB_LEDS   ),
            .NB_SW      (NB_SW     ),
            .NB_COUNTER (NB_COUNTER)
        )
        dut (
        .o_led(o_led),
        .o_led_b(o_led_b),
        .o_leg_g(o_led_g),
        .i_sw(i_sw),
        .i_reset(i_reset),
        .clock(clock)
    );

    // Clock 
    always begin
        #5 clock = ~clock;
    end

    
    initial begin
        $dumpfile("tb/tb1.vcd");
        $dumpvars(0, tb1);
      
        i_reset = 1'b0;
        clock = 1'b1;
        #20;

        i_reset = 1'b1;
        #20;

        i_reset = 1'b0;
        #20;

        i_sw = 4'b0000;
        #50;

        i_sw = 4'b0001;
        #500;

        $finish;
    end

endmodule

diseño-digital/prender-leds/tb/tb1.vcd
$date
	Sun Jun 30 23:50:25 2024
$end
$version
	Icarus Verilog
$end
$timescale
	1ps
$end
$scope module tb1 $end
$var wire 4 ! o_led [3:0] $end
$var wire 4 " o_led_b [3:0] $end
$var wire 4 # o_led_g [3:0] $end
$var reg 1 $ clock $end
$var reg 1 % i_reset $end
$var reg 4 & i_sw [3:0] $end
$scope module dut $end
$var wire 1 ' clock $end
$var wire 1 ( connect_c2sr $end
$var wire 4 ) connect_leds [3:0] $end
$var wire 1 * i_reset $end
$var wire 4 + i_sw [3:0] $end
$var wire 4 , o_led [3:0] $end
$var wire 4 - o_led_b [3:0] $end
$var wire 4 . o_leg_g [3:0] $end
$scope module u_count $end
$var wire 1 ' clock $end
$var wire 1 * i_reset $end
$var wire 3 / i_sw [2:0] $end
$var wire 1 ( o_valid $end
$var reg 14 0 counter [13:0] $end
$var reg 14 1 limit_ref [13:0] $end
$var reg 1 2 valid $end
$upscope $end
$scope module u_shiftreg $end
$var wire 1 ' clock $end
$var wire 1 * i_reset $end
$var wire 1 ( i_valid $end
$var wire 4 3 o_led [3:0] $end
$var reg 4 4 shiftRegister [3:0] $end
$upscope $end
$upscope $end
$upscope $end
$enddefinitions $end
#0
$dumpvars
bx 4
bx 3
x2
b1 1
bx 0
bx /
bx .
bx -
bx ,
bx +
0*
bx )
x(
1'
bx &
0%
1$
bx #
bx "
bx !
$end
#5000
0$
0'
#10000
1$
1'
#15000
0$
0'
#20000
b0x #
b0x .
b0x "
b0x -
02
0(
b0 0
b1 4
b1 )
b1 3
b1 !
b1 ,
1$
1'
1%
1*
#25000
0$
0'
#30000
1$
1'
#35000
0$
0'
#40000
1$
1'
0%
0*
#45000
0$
0'
#50000
1$
1'
#55000
0$
0'
#60000
b0 "
b0 -
b1 #
b1 .
b1111 1
b0 /
1$
1'
b0 &
b0 +
#65000
0$
0'
#70000
1$
1'
#75000
0$
0'
#80000
1$
1'
#85000
0$
0'
#90000
1$
1'
#95000
0$
0'
#100000
1$
1'
#105000
0$
0'
#110000
b1 0
b1 /
1$
1'
b1 &
b1 +
#115000
0$
0'
#120000
b10 0
1$
1'
#125000
0$
0'
#130000
b11 0
1$
1'
#135000
0$
0'
#140000
b100 0
1$
1'
#145000
0$
0'
#150000
b101 0
1$
1'
#155000
0$
0'
#160000
b110 0
1$
1'
#165000
0$
0'
#170000
b111 0
1$
1'
#175000
0$
0'
#180000
b1000 0
1$
1'
#185000
0$
0'
#190000
b1001 0
1$
1'
#195000
0$
0'
#200000
b1010 0
1$
1'
#205000
0$
0'
#210000
b1011 0
1$
1'
#215000
0$
0'
#220000
b1100 0
1$
1'
#225000
0$
0'
#230000
b1101 0
1$
1'
#235000
0$
0'
#240000
b1110 0
1$
1'
#245000
0$
0'
#250000
b1111 0
1$
1'
#255000
0$
0'
#260000
12
1(
b0 0
1$
1'
#265000
0$
0'
#270000
b10 #
b10 .
b10 4
b10 )
b10 3
b10 !
b10 ,
02
0(
b1 0
1$
1'
#275000
0$
0'
#280000
b10 0
1$
1'
#285000
0$
0'
#290000
b11 0
1$
1'
#295000
0$
0'
#300000
b100 0
1$
1'
#305000
0$
0'
#310000
b101 0
1$
1'
#315000
0$
0'
#320000
b110 0
1$
1'
#325000
0$
0'
#330000
b111 0
1$
1'
#335000
0$
0'
#340000
b1000 0
1$
1'
#345000
0$
0'
#350000
b1001 0
1$
1'
#355000
0$
0'
#360000
b1010 0
1$
1'
#365000
0$
0'
#370000
b1011 0
1$
1'
#375000
0$
0'
#380000
b1100 0
1$
1'
#385000
0$
0'
#390000
b1101 0
1$
1'
#395000
0$
0'
#400000
b1110 0
1$
1'
#405000
0$
0'
#410000
b1111 0
1$
1'
#415000
0$
0'
#420000
12
1(
b0 0
1$
1'
#425000
0$
0'
#430000
b100 #
b100 .
b100 4
b100 )
b100 3
b100 !
b100 ,
02
0(
b1 0
1$
1'
#435000
0$
0'
#440000
b10 0
1$
1'
#445000
0$
0'
#450000
b11 0
1$
1'
#455000
0$
0'
#460000
b100 0
1$
1'
#465000
0$
0'
#470000
b101 0
1$
1'
#475000
0$
0'
#480000
b110 0
1$
1'
#485000
0$
0'
#490000
b111 0
1$
1'
#495000
0$
0'
#500000
b1000 0
1$
1'
#505000
0$
0'
#510000
b1001 0
1$
1'
#515000
0$
0'
#520000
b1010 0
1$
1'
#525000
0$
0'
#530000
b1011 0
1$
1'
#535000
0$
0'
#540000
b1100 0
1$
1'
#545000
0$
0'
#550000
b1101 0
1$
1'
#555000
0$
0'
#560000
b1110 0
1$
1'
#565000
0$
0'
#570000
b1111 0
1$
1'
#575000
0$
0'
#580000
12
1(
b0 0
1$
1'
#585000
0$
0'
#590000
b1000 #
b1000 .
b1000 4
b1000 )
b1000 3
b1000 !
b1000 ,
02
0(
b1 0
1$
1'
#595000
0$
0'
#600000
b10 0
1$
1'
#605000
0$
0'
#610000
b11 0
1$
1'
