1/first_counter.v
//SPECS 
//4-bit synchronous up counter.
//active high, synchronous reset.
//Active high enable.

// Function : This is a 4 bit up-counter with
// Synchronous active high reset and
// with active high enable signal

module first_counter(
    clock,
    reset,
    enable,
    counter_out
);

input clock, reset, enable;

output [3:0] counter_out ;

wire clock, reset, enable;

reg [3:0] counter_out;

always @(posedge clock)

begin : COUNTER 
    if(reset == 1'b1) 
    begin
        counter_out <=  #1  4'b0000;
    end
    else if (enable == 1'b1) 
    begin
        counter_out <= #1 counter_out + 1;
    end
end

endmodule

1/first_counter_tb.v
`include "first_counter.v"

module first_counter_tb();

reg clock, reset, enable;
wire [3:0] counter_out;

initial begin 
    $dumpfile("first_counter_tb2.vcd");
    $dumpvars(0, first_counter_tb);
    $display ("time\t clk reset enable counter");
    $monitor ("%g\t %b   %b     %b      %b", 
        $time, clock, reset, enable, counter_out);
    clock = 1;
    reset = 0;
    enable = 0;

    #5 reset = 1;
    #10 reset = 0;
    #10 enable = 1;
    #100 enable = 0;

    #5 $finish;
end

always begin
   #5  clock = ~clock; // Toggle clock every 5 ticks
end

// Connect DUT to test bench
first_counter U_counter (
clock,
reset,
enable,
counter_out
);

endmodule

1/first_counter_tb.vcd
$date
	Sun Apr 21 22:19:51 2024
$end
$version
	Icarus Verilog
$end
$timescale
	1s
$end
$scope module first_counter_tb $end
$var wire 4 ! counter_out [3:0] $end
$var reg 1 " clock $end
$var reg 1 # enable $end
$var reg 1 $ reset $end
$scope module U_counter $end
$var wire 1 % clock $end
$var wire 1 & enable $end
$var wire 1 ' reset $end
$var reg 4 ( counter_out [3:0] $end
$scope begin COUNTER $end
$upscope $end
$upscope $end
$upscope $end
$enddefinitions $end
#0
$dumpvars
bx (
0'
0&
1%
0$
0#
1"
bx !
$end
#5
0"
0%
1$
1'
#10
1"
1%
#11
b0 (
b0 !
#15
0"
0%
0$
0'
#20
1"
1%
#25
0"
0%
1#
1&
#30
1"
1%
#31
b1 (
b1 !
#35
0"
0%
#40
1"
1%
#41
b10 (
b10 !
#45
0"
0%
#50
1"
1%
#51
b11 (
b11 !
#55
0"
0%
#60
1"
1%
#61
b100 (
b100 !
#65
0"
0%
#70
1"
1%
#71
b101 (
b101 !
#75
0"
0%
#80
1"
1%
#81
b110 (
b110 !
#85
0"
0%
#90
1"
1%
#91
b111 (
b111 !
#95
0"
0%
#100
1"
1%
#101
b1000 (
b1000 !
#105
0"
0%
#110
1"
1%
#111
b1001 (
b1001 !
#115
0"
0%
#120
1"
1%
#121
b1010 (
b1010 !
#125
0"
0%
0#
0&
